_easy_tcp/__init__.py
easy_tcp/__init__.py
easy_tcp-0.0.8rc10.dist-info/LICENSE.md
easy_tcp-0.0.8rc10.dist-info/METADATA
easy_tcp-0.0.8rc10.dist-info/WHEEL
easy_tcp-0.0.8rc10.dist-info/top_level.txt
easy_tcp-0.0.8rc10.dist-info/RECORD
