Metadata-Version: 2.1
Name: easy-tcp
Version: 0.0.8rc10
Summary: Python TCP WSGI Server
Home-page: https://github.com/joegasewicz/easy-tcp
Author: Joe Gasewicz
Author-email: joegasewicz@gmail.com
License: UNKNOWN
Platform: UNKNOWN
Classifier: Programming Language :: Python :: 3.9
Classifier: Operating System :: Unix
